gocodeo/__init__.py
gocodeo/demo.py
gocodeo/executable.py
gocodeo/generalized.py
gocodeo/generator.py
gocodeo/python_demo.py
gocodeo/train.py
gocodeo-0.4.dist-info/METADATA
gocodeo-0.4.dist-info/WHEEL
gocodeo-0.4.dist-info/entry_points.txt
gocodeo-0.4.dist-info/top_level.txt
gocodeo-0.4.dist-info/RECORD
