Metadata-Version: 2.1
Name: gocodeo
Version: 0.4
Summary: A package to generate unit tests for a file
Author: GoCodeo AI
Requires-Dist: vertexai
Requires-Dist: requests
Requires-Dist: google-cloud-aiplatform
Requires-Dist: google-auth
Requires-Dist: python-dotenv
Requires-Dist: google-cloud-storage
Requires-Dist: pymongo
